egenix_telegram_antispam_bot-0.7.1.dist-info/licenses/LICENSE
telegram_antispam_bot/__init__.py
telegram_antispam_bot/__main__.py
telegram_antispam_bot/antispam_bot.py
telegram_antispam_bot/challenge.py
telegram_antispam_bot/config.py
telegram_antispam_bot/config_helpers.py
egenix_telegram_antispam_bot-0.7.1.dist-info/METADATA
egenix_telegram_antispam_bot-0.7.1.dist-info/WHEEL
egenix_telegram_antispam_bot-0.7.1.dist-info/top_level.txt
egenix_telegram_antispam_bot-0.7.1.dist-info/RECORD
