Metadata-Version: 2.4
Name: egenix-telegram-antispam-bot
Version: 0.7.1
Summary: eGenix Antispam Bot for Telegram
Home-page: https://www.egenix.com/library/telegram-antispam-bot/
Author: eGenix.com Software, Skills and Services GmbH
Author-email: info@egenix.com
Maintainer: eGenix.com Software, Skills and Services GmbH
Maintainer-email: info@egenix.com
License: MIT
Project-URL: Source, https://github.com/egenix/egenix-telegram-antispam-bot
Project-URL: Tracker, https://github.com/eGenix/egenix-telegram-antispam-bot/issues
Classifier: Environment :: Console
Classifier: Environment :: No Input/Output (Daemon)
Classifier: Framework :: AsyncIO
Classifier: Intended Audience :: Developers
Classifier: License :: OSI Approved :: MIT License
Classifier: Natural Language :: English
Classifier: Operating System :: OS Independent
Classifier: Operating System :: POSIX
Classifier: Operating System :: Unix
Classifier: Programming Language :: C
Classifier: Programming Language :: Python
Classifier: Programming Language :: Python :: 3
Classifier: Programming Language :: Python :: 3.9
Classifier: Programming Language :: Python :: 3.10
Classifier: Topic :: Communications
Classifier: Topic :: Communications :: Chat
Classifier: Topic :: Internet
Classifier: Topic :: Software Development
Classifier: Topic :: Software Development :: Libraries
Classifier: Topic :: Software Development :: Libraries :: Application Frameworks
Classifier: Topic :: Software Development :: Libraries :: Python Modules
Classifier: Development Status :: 5 - Production/Stable
Requires-Python: >=3.9
License-File: LICENSE
Requires-Dist: Pyrogram~=2.0
Requires-Dist: TgCrypto~=1.2
Requires-Dist: emoji~=2.14
Dynamic: author
Dynamic: author-email
Dynamic: classifier
Dynamic: description
Dynamic: description-content-type
Dynamic: home-page
Dynamic: license
Dynamic: license-file
Dynamic: maintainer
Dynamic: maintainer-email
Dynamic: project-url
Dynamic: requires-dist
Dynamic: requires-python
Dynamic: summary
